gradient_generator.py
gradient_generator-0.1.1.dist-info/METADATA
gradient_generator-0.1.1.dist-info/WHEEL
gradient_generator-0.1.1.dist-info/top_level.txt
gradient_generator-0.1.1.dist-info/RECORD
