Metadata-Version: 2.1
Name: gradient-generator
Version: 0.1.1
Summary: Generate random but beautiful gradients in a super simple way.
Home-page: https://github.com/marek-vybiral/gradient-generator
Author: Marek Vybíral
Author-email: me@marekvybiral.com
License: MIT
Platform: UNKNOWN
Classifier: License :: OSI Approved :: MIT License
Classifier: Programming Language :: Python :: 3
Classifier: Programming Language :: Python :: 3.9
Requires-Dist: pillow
